atlassian_tea_utils/__init__.py
atlassian_tea_utils/py.typed
atlassian_tea_utils/ai/__init__.py
atlassian_tea_utils/ai/ai.py
atlassian_tea_utils/atlas/__init__.py
atlassian_tea_utils/atlas/auth.py
atlassian_tea_utils/batchupload/__init__.py
atlassian_tea_utils/batchupload/uploader.py
atlassian_tea_utils/iam/__init__.py
atlassian_tea_utils/iam/action_info.py
atlassian_tea_utils/splunk/__init__.py
atlassian_tea_utils/splunk/splunk.py
atlassian_tea_utils/sql/__init__.py
atlassian_tea_utils/sql/config.py
atlassian_tea_utils/sql/databricks.py
atlassian_tea_utils/sql/socrates.py
atlassian_tea_utils-1.1.2.dist-info/AUTHORS
atlassian_tea_utils-1.1.2.dist-info/METADATA
atlassian_tea_utils-1.1.2.dist-info/WHEEL
atlassian_tea_utils-1.1.2.dist-info/pbr.json
atlassian_tea_utils-1.1.2.dist-info/top_level.txt
atlassian_tea_utils-1.1.2.dist-info/RECORD
