Metadata-Version: 2.1
Name: atlassian-tea-utils
Version: 1.1.2
Summary: Trust Engineering utils
License: MIT
Platform: any
Classifier: Development Status :: 4 - Beta
Classifier: Environment :: Console
Classifier: Intended Audience :: Developers
Classifier: Operating System :: OS Independent
Classifier: Programming Language :: Python
Classifier: Programming Language :: Python :: 3
Classifier: Programming Language :: Python :: 3.11
Classifier: Programming Language :: Python :: 3.12
Classifier: License :: OSI Approved :: MIT License
License-File: AUTHORS
Requires-Dist: charset-normalizer <4,>=2
Requires-Dist: databricks-sql-connector ===3.6.0
Requires-Dist: numpy
Requires-Dist: requests <3.0.0
Requires-Dist: retry <1.0.0
Requires-Dist: click
Provides-Extra: ai
Requires-Dist: openai ; extra == 'ai'
